seismic2dreem/__init__.py
seismic2dreem/cli.py
seismic2dreem/dump.py
seismic2dreem/main.py
seismic2dreem/path.py
seismic2dreem/translation.py
seismic2dreem-0.0.6.dist-info/LICENSE
seismic2dreem-0.0.6.dist-info/METADATA
seismic2dreem-0.0.6.dist-info/WHEEL
seismic2dreem-0.0.6.dist-info/entry_points.txt
seismic2dreem-0.0.6.dist-info/top_level.txt
seismic2dreem-0.0.6.dist-info/RECORD
