Metadata-Version: 2.1
Name: seismic2dreem
Version: 0.0.6
Summary: Converts seismic data to dreem format
Home-page: https://github.com/rouskinlab/seismic2dreem
Author: Yves Martin des Taillades for the Rouskin Lab
Author-email: yves@martin.yt
Requires-Python: >=3.9
License-File: LICENSE
Requires-Dist: pandas
Requires-Dist: numpy
Requires-Dist: click
